agliooglio/__init__.py
agliooglio/errors.py
agliooglio/octarin.py
agliooglio/params.py
agliooglio/utils.py
agliooglio/utils_hash.py
agliooglio/datasets/__init__.py
agliooglio/datasets/base_dataset.py
agliooglio/datasets/datasets.py
agliooglio/datasets/utils.py
aglioolio/__init__.py
aglioolio/errors.py
aglioolio/octarin.py
aglioolio/params.py
aglioolio/utils.py
aglioolio/utils_hash.py
aglioolio/datasets/__init__.py
aglioolio/datasets/base_dataset.py
aglioolio/datasets/datasets.py
aglioolio/datasets/utils.py
octarin/__init__.py
octarin/errors.py
octarin/octarin.py
octarin/params.py
octarin/utils.py
octarin/utils_hash.py
octarin/datasets/__init__.py
octarin/datasets/base_dataset.py
octarin/datasets/datasets.py
octarin/datasets/utils.py
taper-0.0.1.dist-info/LICENSE
taper-0.0.1.dist-info/METADATA
taper-0.0.1.dist-info/WHEEL
taper-0.0.1.dist-info/top_level.txt
taper-0.0.1.dist-info/RECORD
