Metadata-Version: 2.1
Name: taper
Version: 0.0.1
Summary: Contains some data
Home-page: https://github.com/greentfrapp/aglioolio
Author: The Taper Authors
Author-email: limsweekiat@gmail.com
License: Apache License 2.0
Keywords: pytorch
Platform: UNKNOWN
Classifier: Development Status :: 2 - Pre-Alpha
Classifier: Intended Audience :: Science/Research
Classifier: Intended Audience :: Education
Classifier: License :: OSI Approved :: Apache Software License
Classifier: Natural Language :: English
Classifier: Programming Language :: Python
Classifier: Programming Language :: Python :: 3
Classifier: Programming Language :: Python :: 3.6
Classifier: Topic :: Scientific/Engineering
Classifier: Topic :: Scientific/Engineering :: Artificial Intelligence
Classifier: Topic :: Scientific/Engineering :: Mathematics
Classifier: Topic :: Scientific/Engineering :: Visualization
Classifier: Topic :: Software Development :: Libraries :: Python Modules
License-File: LICENSE
Requires-Dist: torch (>=1.5.0)
Requires-Dist: numpy
Requires-Dist: requests
Requires-Dist: tqdm
Requires-Dist: dill
Requires-Dist: pandas
